[ 
{"code":"BO", "name": "Bolivia", "nearby": ["AR", "BR", "CL", "PY", "PE","UY"] },
{"code":"BZ", "name": "Belize", "nearby": ["GT", "MX", "HN", "SV"] },
{"code":"IT", "name": "Italy", "nearby": ["AT", "FR", "SM", "SI", "CH", "VA","MT","MC","LI","TN"] },
{"code":"GA", "name": "Gabon", "nearby": ["CM", "CG", "GQ","ST"] },
{"code":"CG", "name": "Congo", "nearby": ["AO", "CM", "CF", "CD", "GA","GQ"] },
{"code":"CL", "name": "Chile", "nearby": ["AR", "BO", "PE","PY"] },
{"code":"CF", "name": "Central African Republic", "nearby": ["CM", "TD", "CG", "CD", "SD"] },
{"code":"FI", "name": "Finland", "nearby": ["NO", "RU", "SE","EE"] },
{"code":"CU", "name": "Cuba", "nearby": ["US","BS","HT","DO","JM"] },
{"code":"GW", "name": "Guinea-Bissau", "nearby": ["GN", "SN","GM","CV","SL"] },
{"code":"IS", "name": "Iceland", "nearby": ["DK","NO","GB","IE","CA"] },
{"code":"BH", "name": "Bahrain", "nearby": ["QA","SA","IR","AE","KW"] },
{"code":"HT", "name": "Haiti", "nearby": ["DO","CU","US","JM","BS"] },
{"code":"CM", "name": "Cameroon", "nearby": ["CF", "TD", "CG", "GQ", "GA", "NG","ST"] },
{"code":"DO", "name": "Dominican Republic", "nearby": ["HT","CU","JM","KN"] },
{"code":"IE", "name": "Ireland", "nearby": ["GB","IS","FR","NL"] },
{"code":"DZ", "name": "Algeria", "nearby": ["LY", "ML", "MR", "MA", "NE", "TN", "EH"] },
{"code":"TD", "name": "Chad", "nearby": ["CM", "CF", "LY", "NE", "NG", "SD"] },
{"code":"DE", "name": "Germany", "nearby": ["AT", "BE", "CZ", "DK", "FR", "LU", "NL", "PL", "CH","SE","LI"] },
{"code":"ET", "name": "Ethiopia", "nearby": ["DJ", "ER", "KE", "SO",  "SD"] },
{"code":"AF", "name": "Afghanistan", "nearby": ["CN", "IR", "PK", "TJ", "TM", "UZ"] },
{"code":"AZ", "name": "Azerbaijan", "nearby": ["AM", "GE", "IR", "RU", "TR"] },
{"code":"BA", "name": "Bosnia And Herzegovina", "nearby": ["HR", "ME", "RS","SI"] },
{"code":"HR", "name": "Croatia", "nearby": ["BA", "HU", "ME", "RS", "SI","HR"] },
{"code":"VA", "name": "Holy See (Vatican City State)", "nearby": ["IT","FR","SM","MC"] },
{"code":"DM", "name": "Dominica", "nearby": ["LC","VC","GD","AG","KN"] },
{"code":"KI", "name": "Kiribati", "nearby": ["MH","TV","NR","WS","FM"] },
{"code":"BN", "name": "Brunei Darussalam", "nearby": ["MY","PH","SG","ID"] },
{"code":"IR", "name": "Iran, Islamic Republic Of", "nearby": ["AF", "AM", "AZ", "IQ", "PK", "TR", "TM","BH","QA","KW","OM"] },
{"code":"EG", "name": "Egypt", "nearby": ["IL", "LY",  "SD","SA"] },
{"code":"CN", "name": "China", "nearby": ["AF", "BT", "IN", "KZ", "KG", "LA", "MN", "MM", "NP", "KP", "PK", "RU", "TJ", "VN","TW","KR"] },
{"code":"BT", "name": "Bhutan", "nearby": ["CN", "IN","NP","BD"] },
{"code":"AU", "name": "Australia", "nearby": ["NZ","PG","ID","TL"] },
{"code":"AL", "name": "Albania", "nearby": ["GR",  "MK", "ME", "RS"] },
{"code":"GR", "name": "Greece", "nearby": ["AL", "BG", "MK", "TR","CY","MT"] },
{"code":"BB", "name": "Barbados", "nearby": ["VC","TT","LC","GD"] },
{"code":"CO", "name": "Colombia", "nearby": ["BR", "EC", "PA", "PE", "VE","GY"] },
{"code":"CR", "name": "Costa Rica", "nearby": ["NI", "PA","HN","SV"] },
{"code":"BR", "name": "Brazil", "nearby": ["AR", "BO", "CO", "GY", "PY", "PE", "SR", "UY", "VE","EC"] },
{"code":"KH", "name": "Cambodia", "nearby": ["LA", "TH", "VN","MM"] },
{"code":"BJ", "name": "Benin", "nearby": ["BF", "NE", "NG", "TG","GH"] },
{"code":"BE", "name": "Belgium", "nearby": ["FR", "DE", "LU", "NL","GB"] },
{"code":"KM", "name": "Comoros", "nearby": ["MG","SC","MU","MZ"] },
{"code":"KZ", "name": "Kazakhstan", "nearby": ["CN", "KG", "RU", "TM", "UZ","MN"] },
{"code":"GY", "name": "Guyana", "nearby": ["BR", "SR", "VE","CO"] },
{"code":"JP", "name": "Japan", "nearby": ["KR","TW","KP","RU"] },
{"code":"GN", "name": "Guinea", "nearby": ["GW", "CI", "LR", "ML", "SN", "SL","GM"] },
{"code":"CV", "name": "Cape Verde", "nearby": ["SN","MR","GM","GW"] },
{"code":"CD", "name": "Congo, Democratic Republic", "nearby": ["AO", "BI", "CF", "CG", "RW",  "TZ", "UG", "ZM"] },
{"code":"BG", "name": "Bulgaria", "nearby": ["GR", "MK", "RO", "RS", "TR","MD"] },
{"code":"CY", "name": "Cyprus", "nearby": ["TR","GR","SY","LB"] },
{"code":"IN", "name": "India", "nearby": ["BD", "BT", "CN", "MM", "NP", "PK","MV","LK"] },
{"code":"CI", "name": "Cote D'Ivoire", "nearby": ["BF", "GH", "GN", "LR", "ML","SL"] },
{"code":"CA", "name": "Canada", "nearby": ["US","RU","MX","IS"] },
{"code":"DJ", "name": "Djibouti", "nearby": ["ER", "ET", "SO","YE"] },
{"code":"FR", "name": "France", "nearby": ["AD", "BE", "DE", "IT", "LU", "MC", "ES", "CH","VA","PT","NL","GB","IE"] },
{"code":"IL", "name": "Israel", "nearby": ["EG", "JO", "LB",  "SY"] },
{"code":"SV", "name": "El Salvador", "nearby": ["GT", "HN", "BZ","CR","NI"] },
{"code":"BF", "name": "Burkina Faso", "nearby": ["BJ", "GH", "CI", "ML", "NE", "TG"] },
{"code":"GQ", "name": "Equatorial Guinea", "nearby": ["CM", "GA","ST","CG"] },
{"code":"JO", "name": "Jordan", "nearby": ["IQ", "IL",  "SA", "SY","LB"] },
{"code":"FJ", "name": "Fiji", "nearby": ["VU","TO","WS","NZ"] },
{"code":"AR", "name": "Argentina", "nearby": ["BO", "BR", "CL", "PY", "UY"] },
{"code":"BY", "name": "Belarus", "nearby": ["LV", "LT", "PL", "RU", "UA"] },
{"code":"BW", "name": "Botswana", "nearby": ["NA", "ZA", "ZW","LS"] },
{"code":"JM", "name": "Jamaica", "nearby": ["CU","HT","BS","DO"] },
{"code":"IQ", "name": "Iraq", "nearby": ["IR", "JO", "KW", "SA", "SY", "TR"] },
{"code":"AM", "name": "Armenia", "nearby": ["AZ", "GE", "IR", "TR"] },
{"code":"GH", "name": "Ghana", "nearby": ["BF", "CI", "TG","BJ"] },
{"code":"CZ", "name": "Czech Republic", "nearby": ["AT", "DE", "PL", "SK"] },
{"code":"EE", "name": "Estonia", "nearby": ["LV", "RU","FI","LT"] },
{"code":"GT", "name": "Guatemala", "nearby": ["BZ", "SV", "HN", "MX"] },
{"code":"AG", "name": "Antigua And Barbuda", "nearby": ["DM","KN","LC","VC"] },
{"code":"AO", "name": "Angola", "nearby": ["CG", "CD", "NA", "ZM"] },
{"code":"KE", "name": "Kenya", "nearby": ["ET", "SO",  "TZ", "UG"] },
{"code":"AT", "name": "Austria", "nearby": ["CZ", "DE", "HU", "IT", "LI", "SK", "SI", "CH"] },
{"code":"BS", "name": "Bahamas", "nearby": ["CU","US","JM","HT"] },
{"code":"BI", "name": "Burundi", "nearby": ["CD", "RW", "TZ","UG"] },
{"code":"DK", "name": "Denmark", "nearby": ["DE","IS","SE","NO"] },
{"code":"ID", "name": "Indonesia", "nearby": ["TL", "MY", "PG","PW","SG","AU","BN"] },
{"code":"HU", "name": "Hungary", "nearby": ["AT", "HR", "RO", "RS", "SK", "SI", "UA"] },
{"code":"EC", "name": "Ecuador", "nearby": ["CO", "PE","BR","VE"] },
{"code":"GM", "name": "Gambia", "nearby": ["SN","GW","GN","ML","CV"] },
{"code":"BD", "name": "Bangladesh", "nearby": ["IN", "MM","NP","BT","MV","LK"] },
{"code":"AD", "name": "Andorra", "nearby": ["FR", "ES","PT","MC"] },
{"code":"GE", "name": "Georgia", "nearby": ["AM", "AZ", "RU", "TR"] },
{"code":"GD", "name": "Grenada", "nearby": ["DM","VC","TT","LC","BB"] },
{"code":"ER", "name": "Eritrea", "nearby": ["DJ", "ET", "SD","SO"] },
{"code":"HN", "name": "Honduras", "nearby": ["SV", "GT", "NI", "BZ","CR"] },
{"code":"KW", "name": "Kuwait", "nearby": ["IQ", "SA","IR","BH"] },
{"code":"KG", "name": "Kyrgyzstan", "nearby": ["CN", "KZ", "TJ", "UZ","MN"] },
{"code":"LA", "name": "Lao People's Democratic Republic", "nearby": ["KH", "CN", "MM", "TH", "VN"] },
{"code":"LV", "name": "Latvia", "nearby": ["BY", "EE", "LT", "RU"] },
{"code":"LB", "name": "Lebanon", "nearby": ["IL", "SY","CY","JO"] },
{"code":"LS", "name": "Lesotho", "nearby": ["ZA","SZ","BW","MZ"] },
{"code":"LR", "name": "Liberia", "nearby": ["GN", "CI", "SL","ML"] },
{"code":"LY", "name": "Libyan Arab Jamahiriya", "nearby": ["DZ", "TD", "EG", "NE", "SD", "TN","MT"] },
{"code":"LI", "name": "Liechtenstein", "nearby": ["AT", "CH","IT","DE"] },
{"code":"KR", "name": "South Korea", "nearby": ["KP","JP","TW","CN"] },
{"code":"SC", "name": "Seychelles", "nearby": ["KM","MU","MG","TZ"] },
{"code":"VN", "name": "Viet Nam", "nearby": ["KH", "CN", "LA","TH"] },
{"code":"SA", "name": "Saudi Arabia", "nearby": ["IQ", "JO", "KW", "OM", "QA", "AE", "YE","BH","EG"] },
{"code":"SY", "name": "Syrian Arab Republic", "nearby": ["IQ", "IL", "JO", "LB", "TR","CY"] },
{"code":"MU", "name": "Mauritius", "nearby": ["MG","KM","SC","MZ"] },
{"code":"SK", "name": "Slovakia", "nearby": ["AT", "CZ", "HU", "PL", "UA"] },
{"code":"ME", "name": "Montenegro", "nearby": ["AL", "BA", "HR",  "RS"] },
{"code":"ZA", "name": "South Africa", "nearby": ["BW", "LS", "MZ", "NA", "SZ", "ZW"] },
{"code":"MW", "name": "Malawi", "nearby": ["MZ", "TZ", "ZM","ZW"] },
{"code":"TG", "name": "Togo", "nearby": ["BJ", "BF", "GH","NG"] },
{"code":"YE", "name": "Yemen", "nearby": ["OM", "SA","DJ","SO"] },
{"code":"RS", "name": "Serbia", "nearby": ["AL", "BA", "BG", "HR", "HU",  "MK", "ME", "RO"] },
{"code":"SL", "name": "Sierra Leone", "nearby": ["GN", "LR","CI","GW"] },
{"code":"CH", "name": "Switzerland", "nearby": ["AT", "FR", "DE", "IT", "LI"] },
{"code":"NI", "name": "Nicaragua", "nearby": ["CR", "HN","PA","SV"] },
{"code":"MC", "name": "Monaco", "nearby": ["FR","IT","SM","ES","VA","AD"] },
{"code":"NO", "name": "Norway", "nearby": ["FI", "RU", "SE","IS","DK"] },
{"code":"MR", "name": "Mauritania", "nearby": ["DZ", "ML", "SN", "EH","CV"] },
{"code":"UG", "name": "Uganda", "nearby": ["CD", "KE", "RW","BI","TZ"] },
{"code":"PK", "name": "Pakistan", "nearby": ["AF", "CN", "IN", "IR","MV"] },
{"code":"SO", "name": "Somalia", "nearby": ["DJ", "ET", "KE","YE","ER"] },
{"code":"MZ", "name": "Mozambique", "nearby": ["MW", "ZA", "SZ", "TZ", "ZM", "ZW","MU","LS","MG","KM"] },
{"code":"UZ", "name": "Uzbekistan", "nearby": ["AF", "KZ", "KG", "TJ", "TM"] },
{"code":"MG", "name": "Madagascar", "nearby": ["KM","MU","SC","MZ"] },
{"code":"TL", "name": "Timor-Leste", "nearby": ["ID","AU","PG","MY"] },
{"code":"ML", "name": "Mali", "nearby": ["DZ", "BF", "GN", "CI", "MR", "NE", "SN","GM","LR"] },
{"code":"SZ", "name": "Swaziland", "nearby": ["MZ", "ZA","LS","ZW"] },
{"code":"MM", "name": "Myanmar", "nearby": ["BD", "CN", "IN", "LA", "TH","KH"] },
{"code":"PL", "name": "Poland", "nearby": ["BY", "CZ", "DE", "LT", "RU", "SK", "UA"] },
{"code":"MH", "name": "Marshall Islands", "nearby": ["KI","FM","NR","SB"] },
{"code":"FM", "name": "Micronesia, Federated States Of", "nearby": ["PW","MH","NR","KI"] },
{"code":"TW", "name": "Taiwan", "nearby": ["CN","PH","JP","KR"] },
{"code":"TM", "name": "Turkmenistan", "nearby": ["AF", "IR", "KZ", "UZ"] },
{"code":"LU", "name": "Luxembourg", "nearby": ["BE", "FR", "DE","NL"] },
{"code":"GB", "name": "United Kingdom", "nearby": ["IE","IS","FR","BE"] },
{"code":"VE", "name": "Venezuela", "nearby": ["BR", "CO", "GY","SR","PA","EC","TT"] },
{"code":"PA", "name": "Panama", "nearby": ["CO", "CR","NI","VE"] },
{"code":"RO", "name": "Romania", "nearby": ["BG", "HU", "MD", "RS", "UA"] },
{"code":"TZ", "name": "Tanzania", "nearby": ["BI", "CD", "KE", "MW", "MZ", "RW", "UG", "ZM","SC"] },
{"code":"ES", "name": "Spain", "nearby": ["AD", "FR", "MA", "PT","MC","EH"] },
{"code":"AE", "name": "United Arab Emirates", "nearby": ["OM", "SA","BH","QA"] },
{"code":"TT", "name": "Trinidad And Tobago", "nearby": ["BB","GD","SR","VE"] },
{"code":"NL", "name": "Netherlands", "nearby": ["BE", "DE","GB","FR","IE","LU"] },
{"code":"TN", "name": "Tunisia", "nearby": ["DZ", "LY","MT","IT"] },
{"code":"TJ", "name": "Tajikistan", "nearby": ["AF", "CN", "KG", "UZ"] },
{"code":"NG", "name": "Nigeria", "nearby": ["BJ", "CM", "TD", "NE","ST","TG"] },
{"code":"SB", "name": "Solomon Islands", "nearby": ["PG","VU","NR","TV","MH"] },
{"code":"MX", "name": "Mexico", "nearby": ["BZ", "GT", "US","CA"] },
{"code":"SI", "name": "Slovenia", "nearby": ["AT", "HR", "HU", "IT","BA"] },
{"code":"WS", "name": "Samoa", "nearby": ["KI","TO","FJ","TV"] },
{"code":"ZW", "name": "Zimbabwe", "nearby": ["BW", "MZ", "ZA", "ZM","SZ","MW"] },
{"code":"MK", "name": "Macedonia", "nearby": ["AL", "BG", "GR",  "RS"] },
{"code":"VU", "name": "Vanuatu", "nearby": ["FJ","SB","TV","TO","NZ"] },
{"code":"MY", "name": "Malaysia", "nearby": ["BN", "ID", "TH", "PH","SG","PW","TL"] },
{"code":"SR", "name": "Suriname", "nearby": ["BR", "GY","VE","TT"] },
{"code":"TO", "name": "Tonga", "nearby": ["FJ","NZ","VU","WS"] },
{"code":"PE", "name": "Peru", "nearby": ["BO", "BR", "CL", "CO", "EC"] },
{"code":"SG", "name": "Singapore", "nearby": ["MY","ID","BN","TH"] },
{"code":"NE", "name": "Niger", "nearby": ["DZ", "BJ", "BF", "TD", "LY", "ML", "NG"] },
{"code":"KN", "name": "Saint Kitts And Nevis", "nearby": ["AG","DM","LC","DO"] },
{"code":"MN", "name": "Mongolia", "nearby": ["CN", "RU","KZ","KG"] },
{"code":"PT", "name": "Portugal", "nearby": ["ES","MA","FR","AD"] },
{"code":"UA", "name": "Ukraine", "nearby": ["BY", "HU", "MD", "PL", "RO", "RU", "SK"] },
{"code":"MD", "name": "Moldova", "nearby": ["RO", "UA","BG","RU"] },
{"code":"PG", "name": "Papua New Guinea", "nearby": ["ID","SB","AU","TL"] },
{"code":"RW", "name": "Rwanda", "nearby": ["BI", "CD", "TZ", "UG"] },
{"code":"SN", "name": "Senegal", "nearby": ["GM", "GN", "GW", "ML", "MR","CV"] },
{"code":"SE", "name": "Sweden", "nearby": ["FI", "NO","DK","DE"] },
{"code":"KP", "name": "North Korea", "nearby": ["CN", "RU", "KR","JP"] },
{"code":"SD", "name": "Sudan", "nearby": ["CF", "TD", "EG", "ER", "ET", "LY"] },
{"code":"TV", "name": "Tuvalu", "nearby": ["KI","NR","VU","WS","SB"] },
{"code":"VC", "name": "Saint Vincent And Grenadines", "nearby": ["DM","BB","LC","GD","AG"] },
{"code":"ST", "name": "Sao Tome And Principe", "nearby": ["GA","GQ","CM","NG"] },
{"code":"OM", "name": "Oman", "nearby": ["SA", "AE", "YE","IR"] },
{"code":"UY", "name": "Uruguay", "nearby": ["AR", "BR","PY","BO"] },
{"code":"LK", "name": "Sri Lanka", "nearby": ["MV","IN","BD","NP"] },
{"code":"TH", "name": "Thailand", "nearby": ["KH", "LA", "MY", "MM","SG","VN"] },
{"code":"RU", "name": "Russian Federation", "nearby": ["AZ", "BY", "CN", "EE", "FI", "GE", "KZ", "LV", "LT", "MN", "KP", "NO", "PL", "UA","CA","MD","JP"] },
{"code":"PY", "name": "Paraguay", "nearby": ["AR", "BO", "BR","UY","CL"] },
{"code":"MV", "name": "Maldives", "nearby": ["LK","IN","PK","BD"] },
{"code":"NZ", "name": "New Zealand", "nearby": ["AU","TO","FJ","VU"] },
{"code":"PH", "name": "Philippines", "nearby": ["MY","BN","TW","PW"] },
{"code":"NR", "name": "Nauru", "nearby": ["KI","TV","FM","SB","MH"] },
{"code":"MT", "name": "Malta", "nearby": ["IT","TN","GR","LY"] },
{"code":"US", "name": "United States", "nearby": ["CA", "CU", "MX","BS","HT","NL"] },
{"code":"TR", "name": "Turkey", "nearby": ["AM", "AZ", "BG", "GE", "GR", "IR", "IQ", "SY","CY"] },
{"code":"LC", "name": "Saint Lucia", "nearby": ["DM","VC","KN","BB","GD","AG"] },
{"code":"ZM", "name": "Zambia", "nearby": ["AO", "CD", "MW", "MZ", "NA", "TZ", "ZW"] },
{"code":"LT", "name": "Lithuania", "nearby": ["BY", "LV", "PL", "RU","EE"] },
{"code":"MA", "name": "Morocco", "nearby": ["DZ", "ES", "EH","PT"] },
{"code":"QA", "name": "Qatar", "nearby": ["SA","BH","AE","IR"] },
{"code":"SM", "name": "San Marino", "nearby": ["IT","HR","MC","VA"] },
{"code":"NA", "name": "Namibia", "nearby": ["AO", "BW", "ZA", "ZM"] },
{"code":"PW", "name": "Palau", "nearby": ["FM","ID","PH","MY"] },
{"code":"NP", "name": "Nepal", "nearby": ["CN", "IN","BT","BD","LK"] },
{"code":"EH", "name":"Western Sahara", "nearby":["MA","MR","DZ","ES"]}
]
